[{"url":"https://kindmade.com.tw/material/repu/","status":200,"score":85,"grade":"A","priority":"低","title":"再生PU、再生皮革｜永續材質圖鑑｜善良品牌 ESG 綠色材質目錄","titleLength":32,"description":"環境影響對比：真皮的製程往往涉及大量水、化學素材與碳排放（每平方米約 65–150 kg CO₂e；製造過程中形成高污染廢水）。相比之下，再生皮革最大優勢在於從現有產業剩餘中回收，而非新製，間接減少污染風險。","descriptionLength":104,"h1Count":2,"h1Text":"再生PU | 再生PU","canonical":"https://kindmade.com.tw/material/repu/","imageCount":6,"missingAlt":4,"missingAltRatio":0.6667,"internalLinks":117,"externalLinks":7,"recommendations":["檢查多個 H1 是否造成主題分散，建議保留主要標題為 H1。","大量圖片缺少 alt，建議建立圖片替代文字規則並批次補強。"],"error":""},{"url":"https://kindmade.com.tw/material/recycled-metals/","status":200,"score":85,"grade":"A","priority":"低","title":"再生鋼、再生鋁｜永續材質圖鑑｜善良品牌 ESG 綠色材質目錄","titleLength":30,"description":"業界研究指出，透過創新冶煉與回收流程，可保留金屬的強度與韌性，如鋁合金中進行快速條鑄方式，即便含鐵雜質也能提升材料再製性能。而品牌如 Dell 已大量應用再生鋁、鋼與其他回收金屬於商品零組件與包裝中。","descriptionLength":100,"h1Count":2,"h1Text":"再生鋼、再生鋁 | 再生鋼、再生鋁","canonical":"https://kindmade.com.tw/material/recycled-metals/","imageCount":6,"missingAlt":4,"missingAltRatio":0.6667,"internalLinks":111,"externalLinks":7,"recommendations":["檢查多個 H1 是否造成主題分散，建議保留主要標題為 H1。","大量圖片缺少 alt，建議建立圖片替代文字規則並批次補強。"],"error":""},{"url":"https://kindmade.com.tw/material/bamboofiber/","status":200,"score":85,"grade":"A","priority":"低","title":"竹纖維｜永續材質圖鑑｜善良品牌 ESG 綠色材質目錄","titleLength":26,"description":"你知道嗎？竹子被譽為「地球上最快生長的植物之一」，每年能長高達60公分以上，收割後三至五年即可再生，遠比一般木材環境負擔低。這讓竹子成為天然界中不可多得的可再生資源，是企業追求永續的理想原料。","descriptionLength":96,"h1Count":2,"h1Text":"竹纖維 | 竹纖維","canonical":"https://kindmade.com.tw/material/bamboofiber/","imageCount":15,"missingAlt":13,"missingAltRatio":0.8667,"internalLinks":163,"externalLinks":7,"recommendations":["檢查多個 H1 是否造成主題分散，建議保留主要標題為 H1。","大量圖片缺少 alt，建議建立圖片替代文字規則並批次補強。"],"error":""},{"url":"https://kindmade.com.tw/material/teafiber/","status":200,"score":85,"grade":"A","priority":"低","title":"茶葉渣｜永續材質圖鑑｜善良品牌 ESG 綠色材質目錄","titleLength":26,"description":"每天喝茶，可能都忘了---剩下的茶葉渣去哪了？在台灣，每年茶渣產量高達上千噸，卻多被當作垃圾處理，但最近的研究正揭示它們的隱藏可能——從天然纖維、抗菌因子到茶香記憶，茶葉渣其實是永續材質的秘密武器。","descriptionLength":99,"h1Count":2,"h1Text":"茶葉渣 | 茶葉渣","canonical":"https://kindmade.com.tw/material/teafiber/","imageCount":15,"missingAlt":13,"missingAltRatio":0.8667,"internalLinks":174,"externalLinks":7,"recommendations":["檢查多個 H1 是否造成主題分散，建議保留主要標題為 H1。","大量圖片缺少 alt，建議建立圖片替代文字規則並批次補強。"],"error":""},{"url":"https://kindmade.com.tw/material/coffeefiber/","status":200,"score":85,"grade":"A","priority":"低","title":"咖啡渣｜永續材質圖鑑｜善良品牌 ESG 綠色材質目錄","titleLength":26,"description":"你有沒有想過，那杯咖啡喝完後的渣渣，竟能變身為創意與環保的黃金原料？咖啡渣，這個日常中隨手丟棄的副產品，正逐漸成為綠色禮贈品的新寵，將廢棄物轉化為實用材質，是對抗資源浪費的最佳解答。","descriptionLength":91,"h1Count":2,"h1Text":"咖啡渣 | 咖啡渣","canonical":"https://kindmade.com.tw/material/coffeefiber/","imageCount":15,"missingAlt":13,"missingAltRatio":0.8667,"internalLinks":170,"externalLinks":7,"recommendations":["檢查多個 H1 是否造成主題分散，建議保留主要標題為 H1。","大量圖片缺少 alt，建議建立圖片替代文字規則並批次補強。"],"error":""},{"url":"https://kindmade.com.tw/material/cocoshell/","status":200,"score":85,"grade":"A","priority":"低","title":"椰子殼｜永續材質圖鑑｜善良品牌 ESG 綠色材質目錄","titleLength":26,"description":"椰子殼材質：農業廢棄物的永續再生奇蹟。 你是否知道，椰子殼並非只能當垃圾或燃料？它其實蘊含堅固纖維、抗菌特性與高回收價值，是推動永續禮贈品與環保產品的理想素材。","descriptionLength":80,"h1Count":2,"h1Text":"椰子殼 | 椰子殼","canonical":"https://kindmade.com.tw/material/cocoshell/","imageCount":6,"missingAlt":4,"missingAltRatio":0.6667,"internalLinks":111,"externalLinks":8,"recommendations":["檢查多個 H1 是否造成主題分散，建議保留主要標題為 H1。","大量圖片缺少 alt，建議建立圖片替代文字規則並批次補強。"],"error":""},{"url":"https://kindmade.com.tw/material/pineapple-leather/","status":200,"score":85,"grade":"A","priority":"低","title":"鳳梨皮革｜永續材質圖鑑｜善良品牌 ESG 綠色材質目錄","titleLength":27,"description":"原料來源｜農廢變原料，展現廢料新價值 鳳梨皮革取材自鳳梨採收後剩下的葉片，屬於本來就會被廢棄的農業副產品，不需額外灌溉、施肥、用地，也不搶糧食用途。利用原本會焚燒的鳳梨葉，減少碳排與空汙。一公頃鳳梨田所產廢葉，可製作數百公尺皮革布料。","descriptionLength":117,"h1Count":2,"h1Text":"鳳梨皮革 | 鳳梨皮革","canonical":"https://kindmade.com.tw/material/pineapple-leather/","imageCount":3,"missingAlt":1,"missingAltRatio":0.3333,"internalLinks":96,"externalLinks":7,"recommendations":["檢查多個 H1 是否造成主題分散，建議保留主要標題為 H1。","大量圖片缺少 alt，建議建立圖片替代文字規則並批次補強。"],"error":""},{"url":"https://kindmade.com.tw/material/ricehusk/","status":200,"score":85,"grade":"A","priority":"低","title":"稻殼｜永續材質圖鑑｜善良品牌 ESG 綠色材質目錄","titleLength":25,"description":"稻殼材質：從農業副產品到永續禮贈品的低碳選擇。當我們想到稻米，往往聯想到主食與文化，但在碾米過程中，大量被丟棄的「稻殼」其實是極具潛力的永續材料。將廢棄副產品轉化為可用素材，這就是「循環禮贈品」的精髓。","descriptionLength":101,"h1Count":2,"h1Text":"稻殼 | 稻殼","canonical":"https://kindmade.com.tw/material/ricehusk/","imageCount":15,"missingAlt":13,"missingAltRatio":0.8667,"internalLinks":157,"externalLinks":7,"recommendations":["檢查多個 H1 是否造成主題分散，建議保留主要標題為 H1。","大量圖片缺少 alt，建議建立圖片替代文字規則並批次補強。"],"error":""},{"url":"https://kindmade.com.tw/material/tyvek/","status":200,"score":85,"grade":"A","priority":"低","title":"杜邦紙｜永續材質圖鑑｜善良品牌 ESG 綠色材質目錄","titleLength":26,"description":"「讓輕盈成為永續的起點」輕若羽、韌如盾──這就是杜邦紙的魅力。它不只看似紙，更具布的柔韌和塑膠的功能性，是你沒想過的材料奇蹟。 杜邦紙採用高密度聚乙烯（HDPE）閃速紡絲技術製成，不含塑化劑與黏合劑，透成蜘蛛絲般細緻纖維網絡，打造出防水、透氣、耐撕裂、輕盈無比的材質。","descriptionLength":134,"h1Count":2,"h1Text":"杜邦紙 | 杜邦紙","canonical":"https://kindmade.com.tw/material/tyvek/","imageCount":15,"missingAlt":13,"missingAltRatio":0.8667,"internalLinks":163,"externalLinks":7,"recommendations":["檢查多個 H1 是否造成主題分散，建議保留主要標題為 H1。","大量圖片缺少 alt，建議建立圖片替代文字規則並批次補強。"],"error":""},{"url":"https://kindmade.com.tw/material/ecosilicone/","status":200,"score":85,"grade":"A","priority":"低","title":"環保矽膠｜永續材質圖鑑｜善良品牌 ESG 綠色材質目錄","titleLength":27,"description":"環保矽膠：耐用實用，是低碳生活的無聲支持者。你身邊會靜靜存在一種材質：柔軟又有彈性，能耐高溫、耐冷凍，卻不屬於塑膠也不是布，它就是 環保矽膠。這場顛覆「一次性」的選擇，不喧嘩，卻在日常中悄悄改變我們對「環保產品」的定義。","descriptionLength":110,"h1Count":2,"h1Text":"環保矽膠 | 環保矽膠","canonical":"https://kindmade.com.tw/material/ecosilicone/","imageCount":3,"missingAlt":1,"missingAltRatio":0.3333,"internalLinks":96,"externalLinks":7,"recommendations":["檢查多個 H1 是否造成主題分散，建議保留主要標題為 H1。","大量圖片缺少 alt，建議建立圖片替代文字規則並批次補強。"],"error":""}]